cisco_ip_phone_services/__init__.py
cisco_ip_phone_services/__main__.py
cisco_ip_phone_services/base.py
cisco_ip_phone_services/templates/CiscoIPPhoneDirectory.j2
cisco_ip_phone_services/templates/CiscoIPPhoneError.j2
cisco_ip_phone_services/templates/CiscoIPPhoneExecute.j2
cisco_ip_phone_services/templates/CiscoIPPhoneGraphicFileMenu.j2
cisco_ip_phone_services/templates/CiscoIPPhoneGraphicMenu.j2
cisco_ip_phone_services/templates/CiscoIPPhoneIconFileMenu.j2
cisco_ip_phone_services/templates/CiscoIPPhoneIconMenu.j2
cisco_ip_phone_services/templates/CiscoIPPhoneImage.j2
cisco_ip_phone_services/templates/CiscoIPPhoneImageFile.j2
cisco_ip_phone_services/templates/CiscoIPPhoneInput.j2
cisco_ip_phone_services/templates/CiscoIPPhoneMenu.j2
cisco_ip_phone_services/templates/CiscoIPPhoneResponse.j2
cisco_ip_phone_services/templates/CiscoIPPhoneStatus.j2
cisco_ip_phone_services/templates/CiscoIPPhoneStatusFile.j2
cisco_ip_phone_services/templates/CiscoIPPhoneText.j2
cisco_ip_phone_services-2.0.22.dist-info/LICENSE
cisco_ip_phone_services-2.0.22.dist-info/METADATA
cisco_ip_phone_services-2.0.22.dist-info/WHEEL
cisco_ip_phone_services-2.0.22.dist-info/top_level.txt
cisco_ip_phone_services-2.0.22.dist-info/zip-safe
cisco_ip_phone_services-2.0.22.dist-info/RECORD
