Metadata-Version: 2.1
Name: cisco-ip-phone-services
Version: 2.0.22
Summary: Cisco IP Phone Service Factory
Home-page: https://github.com/nficano/phone-services
Author: Nick Ficano
Author-email: nficano@gmail.com
License: Copyright (c) 2019 Nick Ficano
Requires-Dist: Jinja2 (>=2.10.1)
